vsorter/__init__.py
vsorter/_version.py
vsorter/blink_summary.py
vsorter/fix_file_times.py
vsorter/hello.py
vsorter/mkmp4.py
vsorter/movie2gif.py
vsorter/movie_ctl.js
vsorter/movie_utils.py
vsorter/version_copy.py
vsorter/vsorter.py
vsorter/vsorter_action.py
vsorter/vsorter_flask_app.py
vsorter/vsorter_load.py
video_sorter-0.1.6.dist-info/METADATA
video_sorter-0.1.6.dist-info/WHEEL
video_sorter-0.1.6.dist-info/entry_points.txt
video_sorter-0.1.6.dist-info/top_level.txt
video_sorter-0.1.6.dist-info/RECORD
